[
  {
    "id": 1,
    "title": "كتاب الطهارة وسننها"
  },
  {
    "id": 2,
    "title": "كتاب الصلاة"
  },
  {
    "id": 3,
    "title": "كتاب الأذان والسنة فيها"
  },
  {
    "id": 4,
    "title": "كتاب المساجد والجماعات"
  },
  {
    "id": 5,
    "title": "كتاب إقامة الصلاة والسنة فيها"
  },
  {
    "id": 6,
    "title": "كتاب الجنائز"
  },
  {
    "id": 7,
    "title": "كتاب الصيام"
  },
  {
    "id": 8,
    "title": "كتاب الزكاة"
  },
  {
    "id": 9,
    "title": "كتاب النكاح"
  },
  {
    "id": 10,
    "title": "كتاب الطلاق"
  },
  {
    "id": 11,
    "title": "كتاب الكفارات"
  },
  {
    "id": 12,
    "title": "كتاب التجارات"
  },
  {
    "id": 13,
    "title": "كتاب الأحكام"
  },
  {
    "id": 14,
    "title": "كتاب الهبات"
  },
  {
    "id": 15,
    "title": "كتاب الصدقات"
  },
  {
    "id": 16,
    "title": "كتاب الرهون"
  },
  {
    "id": 17,
    "title": "كتاب الشفعة"
  },
  {
    "id": 18,
    "title": "كتاب اللقطة"
  },
  {
    "id": 19,
    "title": "كتاب العتق"
  },
  {
    "id": 20,
    "title": "كتاب الحدود"
  },
  {
    "id": 21,
    "title": "كتاب الديات"
  },
  {
    "id": 22,
    "title": "كتاب الوصايا"
  },
  {
    "id": 23,
    "title": "كتاب الفرائض"
  },
  {
    "id": 24,
    "title": "كتاب الجهاد"
  },
  {
    "id": 25,
    "title": "كتاب المناسك"
  },
  {
    "id": 26,
    "title": "كتاب الأضاحي"
  },
  {
    "id": 27,
    "title": "كتاب الذبائح"
  },
  {
    "id": 28,
    "title": "كتاب الصيد"
  },
  {
    "id": 29,
    "title": "كتاب الأطعمة"
  },
  {
    "id": 30,
    "title": "كتاب الأشربة"
  },
  {
    "id": 31,
    "title": "كتاب الطب"
  },
  {
    "id": 32,
    "title": "كتاب اللباس"
  },
  {
    "id": 33,
    "title": "كتاب الأدب"
  },
  {
    "id": 34,
    "title": "كتاب الدعاء"
  },
  {
    "id": 35,
    "title": "كتاب تعبير الرؤيا"
  },
  {
    "id": 36,
    "title": "كتاب الفتن"
  },
  {
    "id": 37,
    "title": "كتاب الزهد"
  },
  {
    "id": 0,
    "title": "كتاب المقدمة"
  }
]